hsmm/Effect.py
hsmm/Entities.py
hsmm/Inputpraser.py
hsmm/Level.py
hsmm/Utils.py
hsmm/__init__.py
hsmm/actionparser.py
hsmm/conf/__init__.py
hsmm/conf/config.py
hsmm/conf/effects.json
hsmm/conf/entities.json
hsmm/conf/items.json
hsmm/conf/levels.json
hsmm-0.0.1.dist-info/METADATA
hsmm-0.0.1.dist-info/WHEEL
hsmm-0.0.1.dist-info/top_level.txt
hsmm-0.0.1.dist-info/RECORD
