Metadata-Version: 2.1
Name: hsmm
Version: 0.0.1
Summary: wer das liesst kann lesen
Author: Tim16-sys - Kartoffel096 - HilkopterBob
Author-email: Tim16_sys <author@example.com>, Kartoffel096 <author@example.com>, HilkopterBob <author@example.com>
Classifier: Programming Language :: Python :: 3
Classifier: Operating System :: OS Independent
Requires-Python: >=3.7
